<Namespace Name="System.Web.UI.MobileControls.Adapters">
  <Docs>
    <summary><see cref="N:System.Web.UI.MobileControls.Adapters" />名前空間には、既定の HTML、CHTML、または WML マークアップまたは新しいマークアップ規格または特定のブラウザーやモバイル デバイスの動作を変更するモバイル コントロールのライフ サイクルの段階をオーバーライドするために使用できるクラスが含まれています。  この名前空間の Api は廃止されました。 ASP.NET モバイル アプリケーションを開発する方法については、次を参照してください。、 <see href="http://go.microsoft.com/fwlink/?LinkID=182900">www.asp.net/mobile</see> Web サイトです。</summary>
    <remarks>
      <format type="text/markdown"><![CDATA[  
  
## Remarks  
 <xref:System.Web.UI.MobileControls.Adapters.ControlAdapter>クラスは、直接または間接的に継承によってこの名前空間内の他のすべてのアダプター クラスなど<xref:System.Web.UI.MobileControls.Adapters.HtmlControlAdapter>と<xref:System.Web.UI.MobileControls.Adapters.WmlControlAdapter>、だけでなく<xref:System.Web.UI.MobileControls.Adapters.HtmlPageAdapter>、 <xref:System.Web.UI.MobileControls.Adapters.ChtmlPageAdapter>、および<xref:System.Web.UI.MobileControls.Adapters.WmlPageAdapter>です。  
  
 ]]></format>
    </remarks>
  </Docs>
</Namespace>